Ball/__init__.py
Ball/_cball.cp35-win_amd64.pyd
Ball/bcorsis.py
Ball/bcov.py
Ball/bd.py
Ball/cball.py
Ball/utilize.py
Ball/wrap_c.py
Ball-0.2.9.dist-info/METADATA
Ball-0.2.9.dist-info/WHEEL
Ball-0.2.9.dist-info/top_level.txt
Ball-0.2.9.dist-info/RECORD
