Metadata-Version: 2.1
Name: Ball
Version: 0.2.9
Summary: Ball: A Python Package for Detecting Distribution Difference and Association in Metric Spaces
Home-page: https://github.com/Mamba413/Ball
Author: Jin Zhu
Author-email: zhuj37@mail2.sysu.edu.cn
License: GPL-3
Platform: UNKNOWN
Classifier: Topic :: Scientific/Engineering
Classifier: Topic :: Scientific/Engineering :: Bio-Informatics
Classifier: Topic :: Scientific/Engineering :: Information Analysis
Classifier: Programming Language :: Python
Classifier: Programming Language :: Python :: 3
Classifier: Programming Language :: Python :: 3.5
Classifier: Programming Language :: Python :: 3.6
Classifier: Programming Language :: Python :: 3.7
Requires-Python: >=3.5
Requires-Dist: numpy
Requires-Dist: scikit-learn
Requires-Dist: pygam
